[
  {
    "keyword": "rgb to hex converter",
    "calculatorId": "rgb-to-hex-converter",
    "slug": "rgb-to-hex-converter"
  },
  {
    "keyword": "argb color converter",
    "calculatorId": "rgb-to-hex-converter",
    "slug": "argb-color-converter"
  },
  {
    "keyword": "best rgb to cmyk converter",
    "calculatorId": "rgb-to-hex-converter",
    "slug": "best-rgb-to-cmyk-converter"
  },
  {
    "keyword": "ccccff convert rgb",
    "calculatorId": "rgb-to-hex-converter",
    "slug": "ccccff-convert-rgb"
  },
  {
    "keyword": "change hex color to rgb",
    "calculatorId": "rgb-to-hex-converter",
    "slug": "change-hex-color-to-rgb"
  },
  {
    "keyword": "change hex to rgb",
    "calculatorId": "rgb-to-hex-converter",
    "slug": "change-hex-to-rgb"
  },
  {
    "keyword": "cmyk conversion to pantone",
    "calculatorId": "rgb-to-hex-converter",
    "slug": "cmyk-conversion-to-pantone"
  },
  {
    "keyword": "cmyk conversion to pms",
    "calculatorId": "rgb-to-hex-converter",
    "slug": "cmyk-conversion-to-pms"
  },
  {
    "keyword": "cmyk into rgb",
    "calculatorId": "rgb-to-hex-converter",
    "slug": "cmyk-into-rgb"
  },
  {
    "keyword": "color code converter",
    "calculatorId": "rgb-to-hex-converter",
    "slug": "color-code-converter"
  },
  {
    "keyword": "color code converter hex to rgb",
    "calculatorId": "rgb-to-hex-converter",
    "slug": "color-code-converter-hex-to-rgb"
  },
  {
    "keyword": "color code converter rgb to hex",
    "calculatorId": "rgb-to-hex-converter",
    "slug": "color-code-converter-rgb-to-hex"
  },
  {
    "keyword": "color code to rgb converter",
    "calculatorId": "rgb-to-hex-converter",
    "slug": "color-code-to-rgb-converter"
  },
  {
    "keyword": "color conversion hex to rgb",
    "calculatorId": "rgb-to-hex-converter",
    "slug": "color-conversion-hex-to-rgb"
  },
  {
    "keyword": "color converter hex",
    "calculatorId": "rgb-to-hex-converter",
    "slug": "color-converter-hex"
  },
  {
    "keyword": "color converter rgb to hex",
    "calculatorId": "rgb-to-hex-converter",
    "slug": "color-converter-rgb-to-hex"
  },
  {
    "keyword": "color hex code converter",
    "calculatorId": "rgb-to-hex-converter",
    "slug": "color-hex-code-converter"
  },
  {
    "keyword": "color hexadecimal converter",
    "calculatorId": "rgb-to-hex-converter",
    "slug": "color-hexadecimal-converter"
  },
  {
    "keyword": "color to hex code converter",
    "calculatorId": "rgb-to-hex-converter",
    "slug": "color-to-hex-code-converter"
  },
  {
    "keyword": "colour code converter",
    "calculatorId": "rgb-to-hex-converter",
    "slug": "colour-code-converter"
  },
  {
    "keyword": "convert color code to rgb",
    "calculatorId": "rgb-to-hex-converter",
    "slug": "convert-color-code-to-rgb"
  },
  {
    "keyword": "convert colors to cmyk illustrator",
    "calculatorId": "rgb-to-hex-converter",
    "slug": "convert-colors-to-cmyk-illustrator"
  },
  {
    "keyword": "convert from cmyk to rgb",
    "calculatorId": "rgb-to-hex-converter",
    "slug": "convert-from-cmyk-to-rgb"
  },
  {
    "keyword": "convert from hex to rgb",
    "calculatorId": "rgb-to-hex-converter",
    "slug": "convert-from-hex-to-rgb"
  },
  {
    "keyword": "convert hex code to rgb",
    "calculatorId": "rgb-to-hex-converter",
    "slug": "convert-hex-code-to-rgb"
  },
  {
    "keyword": "convert hex color to pantone",
    "calculatorId": "rgb-to-hex-converter",
    "slug": "convert-hex-color-to-pantone"
  },
  {
    "keyword": "convert hex to pantone illustrator",
    "calculatorId": "rgb-to-hex-converter",
    "slug": "convert-hex-to-pantone-illustrator"
  },
  {
    "keyword": "convert hex to rgb css",
    "calculatorId": "rgb-to-hex-converter",
    "slug": "convert-hex-to-rgb-css"
  },
  {
    "keyword": "convert hex to rgb online",
    "calculatorId": "rgb-to-hex-converter",
    "slug": "convert-hex-to-rgb-online"
  },
  {
    "keyword": "convert hexadecimal to rgb",
    "calculatorId": "rgb-to-hex-converter",
    "slug": "convert-hexadecimal-to-rgb"
  },
  {
    "keyword": "convert html color to rgb",
    "calculatorId": "rgb-to-hex-converter",
    "slug": "convert-html-color-to-rgb"
  },
  {
    "keyword": "convert paint color to hex",
    "calculatorId": "rgb-to-hex-converter",
    "slug": "convert-paint-color-to-hex"
  },
  {
    "keyword": "convert pantone color to rgb",
    "calculatorId": "rgb-to-hex-converter",
    "slug": "convert-pantone-color-to-rgb"
  },
  {
    "keyword": "convert pantone to rgb hex codes",
    "calculatorId": "rgb-to-hex-converter",
    "slug": "convert-pantone-to-rgb-hex-codes"
  },
  {
    "keyword": "convert rgb cmyk",
    "calculatorId": "rgb-to-hex-converter",
    "slug": "convert-rgb-cmyk"
  },
  {
    "keyword": "convert rgb color to cmyk",
    "calculatorId": "rgb-to-hex-converter",
    "slug": "convert-rgb-color-to-cmyk"
  },
  {
    "keyword": "convert rgb pantone",
    "calculatorId": "rgb-to-hex-converter",
    "slug": "convert-rgb-pantone"
  },
  {
    "keyword": "convert rgb to cmyk for printing",
    "calculatorId": "rgb-to-hex-converter",
    "slug": "convert-rgb-to-cmyk-for-printing"
  },
  {
    "keyword": "convert rgb to cmyk in coreldraw",
    "calculatorId": "rgb-to-hex-converter",
    "slug": "convert-rgb-to-cmyk-in-coreldraw"
  },
  {
    "keyword": "convert rgb to cmyk in illustrator",
    "calculatorId": "rgb-to-hex-converter",
    "slug": "convert-rgb-to-cmyk-in-illustrator"
  },
  {
    "keyword": "convert rgb to hex code",
    "calculatorId": "rgb-to-hex-converter",
    "slug": "convert-rgb-to-hex-code"
  },
  {
    "keyword": "convert rgb to munsell",
    "calculatorId": "rgb-to-hex-converter",
    "slug": "convert-rgb-to-munsell"
  },
  {
    "keyword": "convert to rgb illustrator",
    "calculatorId": "rgb-to-hex-converter",
    "slug": "convert-to-rgb-illustrator"
  },
  {
    "keyword": "convert ycbcr to rgb",
    "calculatorId": "rgb-to-hex-converter",
    "slug": "convert-ycbcr-to-rgb"
  },
  {
    "keyword": "converting pantone to rgb",
    "calculatorId": "rgb-to-hex-converter",
    "slug": "converting-pantone-to-rgb"
  },
  {
    "keyword": "css convert hex to rgb",
    "calculatorId": "rgb-to-hex-converter",
    "slug": "css-convert-hex-to-rgb"
  },
  {
    "keyword": "decimal to rgb",
    "calculatorId": "rgb-to-hex-converter",
    "slug": "decimal-to-rgb"
  },
  {
    "keyword": "from rgb to cmyk",
    "calculatorId": "rgb-to-hex-converter",
    "slug": "from-rgb-to-cmyk"
  },
  {
    "keyword": "hash to rgb",
    "calculatorId": "rgb-to-hex-converter",
    "slug": "hash-to-rgb"
  },
  {
    "keyword": "hash to rgb converter",
    "calculatorId": "rgb-to-hex-converter",
    "slug": "hash-to-rgb-converter"
  },
  {
    "keyword": "hex code to pantone converter",
    "calculatorId": "rgb-to-hex-converter",
    "slug": "hex-code-to-pantone-converter"
  },
  {
    "keyword": "hex code translator color",
    "calculatorId": "rgb-to-hex-converter",
    "slug": "hex-code-translator-color"
  },
  {
    "keyword": "hex color calculator",
    "calculatorId": "rgb-to-hex-converter",
    "slug": "hex-color-calculator"
  },
  {
    "keyword": "hex color translator",
    "calculatorId": "rgb-to-hex-converter",
    "slug": "hex-color-translator"
  },
  {
    "keyword": "hex colour converter",
    "calculatorId": "rgb-to-hex-converter",
    "slug": "hex-colour-converter"
  },
  {
    "keyword": "hex into rgb",
    "calculatorId": "rgb-to-hex-converter",
    "slug": "hex-into-rgb"
  },
  {
    "keyword": "hex pantone converter",
    "calculatorId": "rgb-to-hex-converter",
    "slug": "hex-pantone-converter"
  },
  {
    "keyword": "hex ral converter",
    "calculatorId": "rgb-to-hex-converter",
    "slug": "hex-ral-converter"
  },
  {
    "keyword": "hex to argb converter",
    "calculatorId": "rgb-to-hex-converter",
    "slug": "hex-to-argb-converter"
  },
  {
    "keyword": "hex to dulux converter",
    "calculatorId": "rgb-to-hex-converter",
    "slug": "hex-to-dulux-converter"
  },
  {
    "keyword": "hex to named color converter",
    "calculatorId": "rgb-to-hex-converter",
    "slug": "hex-to-named-color-converter"
  },
  {
    "keyword": "hex to pantone converter tool",
    "calculatorId": "rgb-to-hex-converter",
    "slug": "hex-to-pantone-converter-tool"
  },
  {
    "keyword": "hex to pantone tcx",
    "calculatorId": "rgb-to-hex-converter",
    "slug": "hex-to-pantone-tcx"
  },
  {
    "keyword": "hex to ral converter",
    "calculatorId": "rgb-to-hex-converter",
    "slug": "hex-to-ral-converter"
  },
  {
    "keyword": "hex to rgb calculator",
    "calculatorId": "rgb-to-hex-converter",
    "slug": "hex-to-rgb-calculator"
  },
  {
    "keyword": "hex to rgb convertor",
    "calculatorId": "rgb-to-hex-converter",
    "slug": "hex-to-rgb-convertor"
  },
  {
    "keyword": "hex to rgb decimal",
    "calculatorId": "rgb-to-hex-converter",
    "slug": "hex-to-rgb-decimal"
  },
  {
    "keyword": "hex to rgb online",
    "calculatorId": "rgb-to-hex-converter",
    "slug": "hex-to-rgb-online"
  },
  {
    "keyword": "hexachrome to pantone converter",
    "calculatorId": "rgb-to-hex-converter",
    "slug": "hexachrome-to-pantone-converter"
  },
  {
    "keyword": "hexto rgb",
    "calculatorId": "rgb-to-hex-converter",
    "slug": "hexto-rgb"
  },
  {
    "keyword": "hsl color converter",
    "calculatorId": "rgb-to-hex-converter",
    "slug": "hsl-color-converter"
  },
  {
    "keyword": "hsl to rgb converter",
    "calculatorId": "rgb-to-hex-converter",
    "slug": "hsl-to-rgb-converter"
  },
  {
    "keyword": "html to rgb converter",
    "calculatorId": "rgb-to-hex-converter",
    "slug": "html-to-rgb-converter"
  },
  {
    "keyword": "paint color to hex converter",
    "calculatorId": "rgb-to-hex-converter",
    "slug": "paint-color-to-hex-converter"
  },
  {
    "keyword": "pantone converter to hex",
    "calculatorId": "rgb-to-hex-converter",
    "slug": "pantone-converter-to-hex"
  },
  {
    "keyword": "pantone rgb equivalents",
    "calculatorId": "rgb-to-hex-converter",
    "slug": "pantone-rgb-equivalents"
  },
  {
    "keyword": "pantone to cmyk conversion chart",
    "calculatorId": "rgb-to-hex-converter",
    "slug": "pantone-to-cmyk-conversion-chart"
  },
  {
    "keyword": "pantone tpx to rgb",
    "calculatorId": "rgb-to-hex-converter",
    "slug": "pantone-tpx-to-rgb"
  },
  {
    "keyword": "pms color converter to hex",
    "calculatorId": "rgb-to-hex-converter",
    "slug": "pms-color-converter-to-hex"
  },
  {
    "keyword": "pms to cmyk conversion",
    "calculatorId": "rgb-to-hex-converter",
    "slug": "pms-to-cmyk-conversion"
  },
  {
    "keyword": "rgb code converter",
    "calculatorId": "rgb-to-hex-converter",
    "slug": "rgb-code-converter"
  },
  {
    "keyword": "rgb code to hex code converter",
    "calculatorId": "rgb-to-hex-converter",
    "slug": "rgb-code-to-hex-code-converter"
  },
  {
    "keyword": "rgb color code generator",
    "calculatorId": "rgb-to-hex-converter",
    "slug": "rgb-color-code-generator"
  },
  {
    "keyword": "rgb color code to cmyk",
    "calculatorId": "rgb-to-hex-converter",
    "slug": "rgb-color-code-to-cmyk"
  },
  {
    "keyword": "rgb color converter",
    "calculatorId": "rgb-to-hex-converter",
    "slug": "rgb-color-converter"
  },
  {
    "keyword": "rgb color number converter",
    "calculatorId": "rgb-to-hex-converter",
    "slug": "rgb-color-number-converter"
  },
  {
    "keyword": "rgb to cmyk file converter",
    "calculatorId": "rgb-to-hex-converter",
    "slug": "rgb-to-cmyk-file-converter"
  },
  {
    "keyword": "rgb to color code converter",
    "calculatorId": "rgb-to-hex-converter",
    "slug": "rgb-to-color-code-converter"
  },
  {
    "keyword": "rgb to color name converter",
    "calculatorId": "rgb-to-hex-converter",
    "slug": "rgb-to-color-name-converter"
  },
  {
    "keyword": "rgb to hash",
    "calculatorId": "rgb-to-hex-converter",
    "slug": "rgb-to-hash"
  },
  {
    "keyword": "rgb to hex color converter online",
    "calculatorId": "rgb-to-hex-converter",
    "slug": "rgb-to-hex-color-converter-online"
  },
  {
    "keyword": "rgb to hsl converter",
    "calculatorId": "rgb-to-hex-converter",
    "slug": "rgb-to-hsl-converter"
  },
  {
    "keyword": "rgb to pantone color code",
    "calculatorId": "rgb-to-hex-converter",
    "slug": "rgb-to-pantone-color-code"
  },
  {
    "keyword": "rgb to pantone converter online",
    "calculatorId": "rgb-to-hex-converter",
    "slug": "rgb-to-pantone-converter-online"
  },
  {
    "keyword": "rgb to pantone tpg",
    "calculatorId": "rgb-to-hex-converter",
    "slug": "rgb-to-pantone-tpg"
  },
  {
    "keyword": "rgb to rgba converter online",
    "calculatorId": "rgb-to-hex-converter",
    "slug": "rgb-to-rgba-converter-online"
  },
  {
    "keyword": "rgb to tpx",
    "calculatorId": "rgb-to-hex-converter",
    "slug": "rgb-to-tpx"
  },
  {
    "keyword": "rgb to web",
    "calculatorId": "rgb-to-hex-converter",
    "slug": "rgb-to-web"
  },
  {
    "keyword": "sikkens rgb converter",
    "calculatorId": "rgb-to-hex-converter",
    "slug": "sikkens-rgb-converter"
  },
  {
    "keyword": "transform rgb to hex",
    "calculatorId": "rgb-to-hex-converter",
    "slug": "transform-rgb-to-hex"
  },
  {
    "keyword": "translate hex color to rgb",
    "calculatorId": "rgb-to-hex-converter",
    "slug": "translate-hex-color-to-rgb"
  },
  {
    "keyword": "translate hex to rgb",
    "calculatorId": "rgb-to-hex-converter",
    "slug": "translate-hex-to-rgb"
  },
  {
    "keyword": "translate rgb to hex",
    "calculatorId": "rgb-to-hex-converter",
    "slug": "translate-rgb-to-hex"
  },
  {
    "keyword": "turn hex into rgb",
    "calculatorId": "rgb-to-hex-converter",
    "slug": "turn-hex-into-rgb"
  },
  {
    "keyword": "turn rgb into hex",
    "calculatorId": "rgb-to-hex-converter",
    "slug": "turn-rgb-into-hex"
  }
]