[
  {
    "keyword": "bandwidth calculator",
    "calculatorId": "bandwidth-calculator",
    "slug": "bandwidth-calculator"
  },
  {
    "keyword": "internet speed calculator",
    "calculatorId": "bandwidth-calculator",
    "slug": "internet-speed-calculator"
  },
  {
    "keyword": "data speed calculator",
    "calculatorId": "bandwidth-calculator",
    "slug": "data-speed-calculator"
  },
  {
    "keyword": "download speed calculator",
    "calculatorId": "bandwidth-calculator",
    "slug": "download-speed-calculator"
  },
  {
    "keyword": "bandwidth transfer calculator",
    "calculatorId": "bandwidth-calculator",
    "slug": "bandwidth-transfer-calculator"
  },
  {
    "keyword": "business internet speed calculator",
    "calculatorId": "bandwidth-calculator",
    "slug": "business-internet-speed-calculator"
  },
  {
    "keyword": "internet speed calculator mbps",
    "calculatorId": "bandwidth-calculator",
    "slug": "internet-speed-calculator-mbps"
  },
  {
    "keyword": "wifi speed calculator",
    "calculatorId": "bandwidth-calculator",
    "slug": "wifi-speed-calculator"
  },
  {
    "keyword": "digitalocean bandwidth calculator",
    "calculatorId": "bandwidth-calculator",
    "slug": "digitalocean-bandwidth-calculator"
  },
  {
    "keyword": "broadband speed calculator",
    "calculatorId": "bandwidth-calculator",
    "slug": "broadband-speed-calculator"
  },
  {
    "keyword": "internet download speed calculator",
    "calculatorId": "bandwidth-calculator",
    "slug": "internet-download-speed-calculator"
  },
  {
    "keyword": "calculate internet speed needed",
    "calculatorId": "bandwidth-calculator",
    "slug": "calculate-internet-speed-needed"
  },
  {
    "keyword": "internet bandwidth calculator",
    "calculatorId": "bandwidth-calculator",
    "slug": "internet-bandwidth-calculator"
  },
  {
    "keyword": "network bandwidth calculator",
    "calculatorId": "bandwidth-calculator",
    "slug": "network-bandwidth-calculator"
  },
  {
    "keyword": "data speed transfer calculator",
    "calculatorId": "bandwidth-calculator",
    "slug": "data-speed-transfer-calculator"
  },
  {
    "keyword": "internet speed need calculator",
    "calculatorId": "bandwidth-calculator",
    "slug": "internet-speed-need-calculator"
  },
  {
    "keyword": "network throughput calculator",
    "calculatorId": "bandwidth-calculator",
    "slug": "network-throughput-calculator"
  },
  {
    "keyword": "business bandwidth calculator",
    "calculatorId": "bandwidth-calculator",
    "slug": "business-bandwidth-calculator"
  },
  {
    "keyword": "bandwidth calculator file transfer",
    "calculatorId": "bandwidth-calculator",
    "slug": "bandwidth-calculator-file-transfer"
  },
  {
    "keyword": "bandwidth usage calculator",
    "calculatorId": "bandwidth-calculator",
    "slug": "bandwidth-usage-calculator"
  },
  {
    "keyword": "determine internet speed needed",
    "calculatorId": "bandwidth-calculator",
    "slug": "determine-internet-speed-needed"
  },
  {
    "keyword": "internet speed calculator how much do i need",
    "calculatorId": "bandwidth-calculator",
    "slug": "internet-speed-calculator-how-much-do-i-need"
  },
  {
    "keyword": "determine bandwidth",
    "calculatorId": "bandwidth-calculator",
    "slug": "determine-bandwidth"
  },
  {
    "keyword": "calculate my internet speed",
    "calculatorId": "bandwidth-calculator",
    "slug": "calculate-my-internet-speed"
  },
  {
    "keyword": "data transfer bandwidth calculator",
    "calculatorId": "bandwidth-calculator",
    "slug": "data-transfer-bandwidth-calculator"
  },
  {
    "keyword": "isp bandwidth calculator",
    "calculatorId": "bandwidth-calculator",
    "slug": "isp-bandwidth-calculator"
  },
  {
    "keyword": "internet speed estimator",
    "calculatorId": "bandwidth-calculator",
    "slug": "internet-speed-estimator"
  },
  {
    "keyword": "transfer rate calculator bandwidth",
    "calculatorId": "bandwidth-calculator",
    "slug": "transfer-rate-calculator-bandwidth"
  },
  {
    "keyword": "azure bandwidth calculator",
    "calculatorId": "bandwidth-calculator",
    "slug": "azure-bandwidth-calculator"
  },
  {
    "keyword": "gigabit download speed calculator",
    "calculatorId": "bandwidth-calculator",
    "slug": "gigabit-download-speed-calculator"
  },
  {
    "keyword": "network speed calculator",
    "calculatorId": "bandwidth-calculator",
    "slug": "network-speed-calculator"
  },
  {
    "keyword": "bandwidth estimation",
    "calculatorId": "bandwidth-calculator",
    "slug": "bandwidth-estimation"
  },
  {
    "keyword": "calculate how much internet speed i need",
    "calculatorId": "bandwidth-calculator",
    "slug": "calculate-how-much-internet-speed-i-need"
  },
  {
    "keyword": "internet bandwidth calculator per user",
    "calculatorId": "bandwidth-calculator",
    "slug": "internet-bandwidth-calculator-per-user"
  },
  {
    "keyword": "internet calculator speed",
    "calculatorId": "bandwidth-calculator",
    "slug": "internet-calculator-speed"
  },
  {
    "keyword": "bandwidth calculator for data transfer",
    "calculatorId": "bandwidth-calculator",
    "slug": "bandwidth-calculator-for-data-transfer"
  },
  {
    "keyword": "internet speed calculator online",
    "calculatorId": "bandwidth-calculator",
    "slug": "internet-speed-calculator-online"
  },
  {
    "keyword": "web hosting bandwidth calculator",
    "calculatorId": "bandwidth-calculator",
    "slug": "web-hosting-bandwidth-calculator"
  },
  {
    "keyword": "wifi download speed calculator",
    "calculatorId": "bandwidth-calculator",
    "slug": "wifi-download-speed-calculator"
  },
  {
    "keyword": "website bandwidth calculator",
    "calculatorId": "bandwidth-calculator",
    "slug": "website-bandwidth-calculator"
  },
  {
    "keyword": "1080p bandwidth calculator",
    "calculatorId": "bandwidth-calculator",
    "slug": "1080p-bandwidth-calculator"
  },
  {
    "keyword": "10mbps download speed calculator",
    "calculatorId": "bandwidth-calculator",
    "slug": "10mbps-download-speed-calculator"
  },
  {
    "keyword": "1mbps download speed calculator",
    "calculatorId": "bandwidth-calculator",
    "slug": "1mbps-download-speed-calculator"
  },
  {
    "keyword": "2mbps download speed calculator",
    "calculatorId": "bandwidth-calculator",
    "slug": "2mbps-download-speed-calculator"
  },
  {
    "keyword": "2mp cctv camera storage calculator",
    "calculatorId": "bandwidth-calculator",
    "slug": "2mp-cctv-camera-storage-calculator"
  },
  {
    "keyword": "3db bandwidth calculation",
    "calculatorId": "bandwidth-calculator",
    "slug": "3db-bandwidth-calculation"
  },
  {
    "keyword": "4k bandwidth calculator",
    "calculatorId": "bandwidth-calculator",
    "slug": "4k-bandwidth-calculator"
  },
  {
    "keyword": "4k ip camera bandwidth calculator",
    "calculatorId": "bandwidth-calculator",
    "slug": "4k-ip-camera-bandwidth-calculator"
  },
  {
    "keyword": "95th percentile bandwidth calculator",
    "calculatorId": "bandwidth-calculator",
    "slug": "95th-percentile-bandwidth-calculator"
  },
  {
    "keyword": "application bandwidth calculator",
    "calculatorId": "bandwidth-calculator",
    "slug": "application-bandwidth-calculator"
  },
  {
    "keyword": "axis camera bandwidth calculator",
    "calculatorId": "bandwidth-calculator",
    "slug": "axis-camera-bandwidth-calculator"
  },
  {
    "keyword": "azure bandwidth pricing calculator",
    "calculatorId": "bandwidth-calculator",
    "slug": "azure-bandwidth-pricing-calculator"
  },
  {
    "keyword": "backup bandwidth calculator",
    "calculatorId": "bandwidth-calculator",
    "slug": "backup-bandwidth-calculator"
  },
  {
    "keyword": "bandwidth cal",
    "calculatorId": "bandwidth-calculator",
    "slug": "bandwidth-cal"
  },
  {
    "keyword": "bandwidth calculation example",
    "calculatorId": "bandwidth-calculator",
    "slug": "bandwidth-calculation-example"
  },
  {
    "keyword": "bandwidth calculation formula",
    "calculatorId": "bandwidth-calculator",
    "slug": "bandwidth-calculation-formula"
  },
  {
    "keyword": "bandwidth calculation formula in network",
    "calculatorId": "bandwidth-calculator",
    "slug": "bandwidth-calculation-formula-in-network"
  },
  {
    "keyword": "bandwidth calculation from frequency",
    "calculatorId": "bandwidth-calculator",
    "slug": "bandwidth-calculation-from-frequency"
  },
  {
    "keyword": "bandwidth calculation in network",
    "calculatorId": "bandwidth-calculator",
    "slug": "bandwidth-calculation-in-network"
  },
  {
    "keyword": "bandwidth calculator cctv",
    "calculatorId": "bandwidth-calculator",
    "slug": "bandwidth-calculator-cctv"
  },
  {
    "keyword": "bandwidth calculator data transfer",
    "calculatorId": "bandwidth-calculator",
    "slug": "bandwidth-calculator-data-transfer"
  },
  {
    "keyword": "bandwidth calculator for isp",
    "calculatorId": "bandwidth-calculator",
    "slug": "bandwidth-calculator-for-isp"
  },
  {
    "keyword": "bandwidth calculator mbps",
    "calculatorId": "bandwidth-calculator",
    "slug": "bandwidth-calculator-mbps"
  },
  {
    "keyword": "bandwidth calculator online",
    "calculatorId": "bandwidth-calculator",
    "slug": "bandwidth-calculator-online"
  },
  {
    "keyword": "bandwidth calculator per user",
    "calculatorId": "bandwidth-calculator",
    "slug": "bandwidth-calculator-per-user"
  },
  {
    "keyword": "bandwidth calculator time",
    "calculatorId": "bandwidth-calculator",
    "slug": "bandwidth-calculator-time"
  },
  {
    "keyword": "bandwidth calculator tool",
    "calculatorId": "bandwidth-calculator",
    "slug": "bandwidth-calculator-tool"
  },
  {
    "keyword": "bandwidth calculator video",
    "calculatorId": "bandwidth-calculator",
    "slug": "bandwidth-calculator-video"
  },
  {
    "keyword": "bandwidth capacity calculator",
    "calculatorId": "bandwidth-calculator",
    "slug": "bandwidth-capacity-calculator"
  },
  {
    "keyword": "bandwidth computation",
    "calculatorId": "bandwidth-calculator",
    "slug": "bandwidth-computation"
  },
  {
    "keyword": "bandwidth consumption calculator",
    "calculatorId": "bandwidth-calculator",
    "slug": "bandwidth-consumption-calculator"
  },
  {
    "keyword": "bandwidth conversion calculator",
    "calculatorId": "bandwidth-calculator",
    "slug": "bandwidth-conversion-calculator"
  },
  {
    "keyword": "bandwidth converter",
    "calculatorId": "bandwidth-calculator",
    "slug": "bandwidth-converter"
  },
  {
    "keyword": "bandwidth cost calculator",
    "calculatorId": "bandwidth-calculator",
    "slug": "bandwidth-cost-calculator"
  },
  {
    "keyword": "bandwidth download calculator",
    "calculatorId": "bandwidth-calculator",
    "slug": "bandwidth-download-calculator"
  },
  {
    "keyword": "bandwidth estimation calculator",
    "calculatorId": "bandwidth-calculator",
    "slug": "bandwidth-estimation-calculator"
  },
  {
    "keyword": "bandwidth need calculator",
    "calculatorId": "bandwidth-calculator",
    "slug": "bandwidth-need-calculator"
  },
  {
    "keyword": "bandwidth ratio calculation",
    "calculatorId": "bandwidth-calculator",
    "slug": "bandwidth-ratio-calculation"
  },
  {
    "keyword": "bandwidth requirement calculation tool",
    "calculatorId": "bandwidth-calculator",
    "slug": "bandwidth-requirement-calculation-tool"
  },
  {
    "keyword": "bandwidth requirement calculator",
    "calculatorId": "bandwidth-calculator",
    "slug": "bandwidth-requirement-calculator"
  },
  {
    "keyword": "bandwidth sizing calculator",
    "calculatorId": "bandwidth-calculator",
    "slug": "bandwidth-sizing-calculator"
  },
  {
    "keyword": "bandwidth speed calculator",
    "calculatorId": "bandwidth-calculator",
    "slug": "bandwidth-speed-calculator"
  },
  {
    "keyword": "bandwidth streaming calculator",
    "calculatorId": "bandwidth-calculator",
    "slug": "bandwidth-streaming-calculator"
  },
  {
    "keyword": "bandwidth throughput calculator",
    "calculatorId": "bandwidth-calculator",
    "slug": "bandwidth-throughput-calculator"
  },
  {
    "keyword": "bandwidth to download speed calculator",
    "calculatorId": "bandwidth-calculator",
    "slug": "bandwidth-to-download-speed-calculator"
  },
  {
    "keyword": "bandwidth to frequency calculator",
    "calculatorId": "bandwidth-calculator",
    "slug": "bandwidth-to-frequency-calculator"
  },
  {
    "keyword": "bandwidth traffic calculator",
    "calculatorId": "bandwidth-calculator",
    "slug": "bandwidth-traffic-calculator"
  },
  {
    "keyword": "bandwidth transfer time calculator",
    "calculatorId": "bandwidth-calculator",
    "slug": "bandwidth-transfer-time-calculator"
  },
  {
    "keyword": "bandwidth upload calculator",
    "calculatorId": "bandwidth-calculator",
    "slug": "bandwidth-upload-calculator"
  },
  {
    "keyword": "bandwidth usage estimator",
    "calculatorId": "bandwidth-calculator",
    "slug": "bandwidth-usage-estimator"
  },
  {
    "keyword": "bandwidth utilization calculator",
    "calculatorId": "bandwidth-calculator",
    "slug": "bandwidth-utilization-calculator"
  },
  {
    "keyword": "bandwidth website calculator",
    "calculatorId": "bandwidth-calculator",
    "slug": "bandwidth-website-calculator"
  },
  {
    "keyword": "broadband bandwidth calculator",
    "calculatorId": "bandwidth-calculator",
    "slug": "broadband-bandwidth-calculator"
  },
  {
    "keyword": "broadband download speed calculator",
    "calculatorId": "bandwidth-calculator",
    "slug": "broadband-download-speed-calculator"
  },
  {
    "keyword": "broadband speed converter",
    "calculatorId": "bandwidth-calculator",
    "slug": "broadband-speed-converter"
  },
  {
    "keyword": "bw calculator",
    "calculatorId": "bandwidth-calculator",
    "slug": "bw-calculator"
  },
  {
    "keyword": "calculate bandwidth from data rate",
    "calculatorId": "bandwidth-calculator",
    "slug": "calculate-bandwidth-from-data-rate"
  },
  {
    "keyword": "calculate bandwidth from frequency",
    "calculatorId": "bandwidth-calculator",
    "slug": "calculate-bandwidth-from-frequency"
  },
  {
    "keyword": "calculate download speed from bandwidth",
    "calculatorId": "bandwidth-calculator",
    "slug": "calculate-download-speed-from-bandwidth"
  },
  {
    "keyword": "calculate internet speed in mbps",
    "calculatorId": "bandwidth-calculator",
    "slug": "calculate-internet-speed-in-mbps"
  },
  {
    "keyword": "calculate my broadband speed",
    "calculatorId": "bandwidth-calculator",
    "slug": "calculate-my-broadband-speed"
  },
  {
    "keyword": "calculate my wifi speed",
    "calculatorId": "bandwidth-calculator",
    "slug": "calculate-my-wifi-speed"
  },
  {
    "keyword": "calculate network bandwidth requirements",
    "calculatorId": "bandwidth-calculator",
    "slug": "calculate-network-bandwidth-requirements"
  },
  {
    "keyword": "calculate network speed transfer rate",
    "calculatorId": "bandwidth-calculator",
    "slug": "calculate-network-speed-transfer-rate"
  },
  {
    "keyword": "calculate streaming data usage",
    "calculatorId": "bandwidth-calculator",
    "slug": "calculate-streaming-data-usage"
  },
  {
    "keyword": "calculating throughput network",
    "calculatorId": "bandwidth-calculator",
    "slug": "calculating-throughput-network"
  },
  {
    "keyword": "calculator speed internet",
    "calculatorId": "bandwidth-calculator",
    "slug": "calculator-speed-internet"
  },
  {
    "keyword": "camera bandwidth calculator axis",
    "calculatorId": "bandwidth-calculator",
    "slug": "camera-bandwidth-calculator-axis"
  },
  {
    "keyword": "cctv bitrate calculator",
    "calculatorId": "bandwidth-calculator",
    "slug": "cctv-bitrate-calculator"
  },
  {
    "keyword": "cctv camera bitrate calculator",
    "calculatorId": "bandwidth-calculator",
    "slug": "cctv-camera-bitrate-calculator"
  },
  {
    "keyword": "cctv network bandwidth calculator",
    "calculatorId": "bandwidth-calculator",
    "slug": "cctv-network-bandwidth-calculator"
  },
  {
    "keyword": "cdn bandwidth calculator",
    "calculatorId": "bandwidth-calculator",
    "slug": "cdn-bandwidth-calculator"
  },
  {
    "keyword": "cir bandwidth calculator",
    "calculatorId": "bandwidth-calculator",
    "slug": "cir-bandwidth-calculator"
  },
  {
    "keyword": "cloud bandwidth calculator",
    "calculatorId": "bandwidth-calculator",
    "slug": "cloud-bandwidth-calculator"
  },
  {
    "keyword": "connection speed calculator",
    "calculatorId": "bandwidth-calculator",
    "slug": "connection-speed-calculator"
  },
  {
    "keyword": "data bandwidth calculator",
    "calculatorId": "bandwidth-calculator",
    "slug": "data-bandwidth-calculator"
  },
  {
    "keyword": "data download speed calculator",
    "calculatorId": "bandwidth-calculator",
    "slug": "data-download-speed-calculator"
  },
  {
    "keyword": "data speed converter",
    "calculatorId": "bandwidth-calculator",
    "slug": "data-speed-converter"
  },
  {
    "keyword": "data usage calculator kbps",
    "calculatorId": "bandwidth-calculator",
    "slug": "data-usage-calculator-kbps"
  },
  {
    "keyword": "determining bandwidth requirements",
    "calculatorId": "bandwidth-calculator",
    "slug": "determining-bandwidth-requirements"
  },
  {
    "keyword": "docsis throughput calculator",
    "calculatorId": "bandwidth-calculator",
    "slug": "docsis-throughput-calculator"
  },
  {
    "keyword": "download and upload speed calculator",
    "calculatorId": "bandwidth-calculator",
    "slug": "download-and-upload-speed-calculator"
  },
  {
    "keyword": "download internet speed calculator",
    "calculatorId": "bandwidth-calculator",
    "slug": "download-internet-speed-calculator"
  },
  {
    "keyword": "download speed calculator mb s",
    "calculatorId": "bandwidth-calculator",
    "slug": "download-speed-calculator-mb-s"
  },
  {
    "keyword": "download upload speed calculator",
    "calculatorId": "bandwidth-calculator",
    "slug": "download-upload-speed-calculator"
  },
  {
    "keyword": "dsl bandwidth calculator",
    "calculatorId": "bandwidth-calculator",
    "slug": "dsl-bandwidth-calculator"
  },
  {
    "keyword": "egress bandwidth calculator",
    "calculatorId": "bandwidth-calculator",
    "slug": "egress-bandwidth-calculator"
  },
  {
    "keyword": "estimate bandwidth usage calculator",
    "calculatorId": "bandwidth-calculator",
    "slug": "estimate-bandwidth-usage-calculator"
  },
  {
    "keyword": "estimate internet speed",
    "calculatorId": "bandwidth-calculator",
    "slug": "estimate-internet-speed"
  },
  {
    "keyword": "estimating bandwidth requirements",
    "calculatorId": "bandwidth-calculator",
    "slug": "estimating-bandwidth-requirements"
  },
  {
    "keyword": "ethernet bandwidth calculator",
    "calculatorId": "bandwidth-calculator",
    "slug": "ethernet-bandwidth-calculator"
  },
  {
    "keyword": "free bandwidth calculator",
    "calculatorId": "bandwidth-calculator",
    "slug": "free-bandwidth-calculator"
  },
  {
    "keyword": "fsk bandwidth calculator",
    "calculatorId": "bandwidth-calculator",
    "slug": "fsk-bandwidth-calculator"
  },
  {
    "keyword": "genetec video storage calculator",
    "calculatorId": "bandwidth-calculator",
    "slug": "genetec-video-storage-calculator"
  },
  {
    "keyword": "google bandwidth calculator",
    "calculatorId": "bandwidth-calculator",
    "slug": "google-bandwidth-calculator"
  },
  {
    "keyword": "google cloud bandwidth calculator",
    "calculatorId": "bandwidth-calculator",
    "slug": "google-cloud-bandwidth-calculator"
  },
  {
    "keyword": "h 264 bandwidth calculator",
    "calculatorId": "bandwidth-calculator",
    "slug": "h-264-bandwidth-calculator"
  },
  {
    "keyword": "h 264 streaming bandwidth calculator",
    "calculatorId": "bandwidth-calculator",
    "slug": "h-264-streaming-bandwidth-calculator"
  },
  {
    "keyword": "h 265 bandwidth calculator",
    "calculatorId": "bandwidth-calculator",
    "slug": "h-265-bandwidth-calculator"
  },
  {
    "keyword": "h264 storage calculator",
    "calculatorId": "bandwidth-calculator",
    "slug": "h264-storage-calculator"
  },
  {
    "keyword": "hikvision ip camera bandwidth calculator",
    "calculatorId": "bandwidth-calculator",
    "slug": "hikvision-ip-camera-bandwidth-calculator"
  },
  {
    "keyword": "home internet bandwidth calculator",
    "calculatorId": "bandwidth-calculator",
    "slug": "home-internet-bandwidth-calculator"
  },
  {
    "keyword": "hosting bandwidth calculator",
    "calculatorId": "bandwidth-calculator",
    "slug": "hosting-bandwidth-calculator"
  },
  {
    "keyword": "hotel bandwidth calculator",
    "calculatorId": "bandwidth-calculator",
    "slug": "hotel-bandwidth-calculator"
  },
  {
    "keyword": "internet bandwidth requirement calculator",
    "calculatorId": "bandwidth-calculator",
    "slug": "internet-bandwidth-requirement-calculator"
  },
  {
    "keyword": "internet speed cal",
    "calculatorId": "bandwidth-calculator",
    "slug": "internet-speed-cal"
  },
  {
    "keyword": "internet speed calculate",
    "calculatorId": "bandwidth-calculator",
    "slug": "internet-speed-calculate"
  },
  {
    "keyword": "internet speed calculation formula",
    "calculatorId": "bandwidth-calculator",
    "slug": "internet-speed-calculation-formula"
  },
  {
    "keyword": "internet speed calculator for pc",
    "calculatorId": "bandwidth-calculator",
    "slug": "internet-speed-calculator-for-pc"
  },
  {
    "keyword": "internet speed conversion calculator",
    "calculatorId": "bandwidth-calculator",
    "slug": "internet-speed-conversion-calculator"
  },
  {
    "keyword": "internet speed requirement calculator",
    "calculatorId": "bandwidth-calculator",
    "slug": "internet-speed-requirement-calculator"
  },
  {
    "keyword": "internet speed test calculator",
    "calculatorId": "bandwidth-calculator",
    "slug": "internet-speed-test-calculator"
  },
  {
    "keyword": "internet speed test in mb s",
    "calculatorId": "bandwidth-calculator",
    "slug": "internet-speed-test-in-mb-s"
  },
  {
    "keyword": "internet speed transfer calculator",
    "calculatorId": "bandwidth-calculator",
    "slug": "internet-speed-transfer-calculator"
  },
  {
    "keyword": "internet speed usage calculator",
    "calculatorId": "bandwidth-calculator",
    "slug": "internet-speed-usage-calculator"
  },
  {
    "keyword": "internet traffic calculator",
    "calculatorId": "bandwidth-calculator",
    "slug": "internet-traffic-calculator"
  },
  {
    "keyword": "iops bandwidth calculator",
    "calculatorId": "bandwidth-calculator",
    "slug": "iops-bandwidth-calculator"
  },
  {
    "keyword": "ip bandwidth calculator",
    "calculatorId": "bandwidth-calculator",
    "slug": "ip-bandwidth-calculator"
  },
  {
    "keyword": "ip camera bandwidth calculator hikvision",
    "calculatorId": "bandwidth-calculator",
    "slug": "ip-camera-bandwidth-calculator-hikvision"
  },
  {
    "keyword": "ip camera bitrate calculator",
    "calculatorId": "bandwidth-calculator",
    "slug": "ip-camera-bitrate-calculator"
  },
  {
    "keyword": "ip camera data usage calculator",
    "calculatorId": "bandwidth-calculator",
    "slug": "ip-camera-data-usage-calculator"
  },
  {
    "keyword": "ip camera traffic calculator",
    "calculatorId": "bandwidth-calculator",
    "slug": "ip-camera-traffic-calculator"
  },
  {
    "keyword": "iptv bandwidth calculator",
    "calculatorId": "bandwidth-calculator",
    "slug": "iptv-bandwidth-calculator"
  },
  {
    "keyword": "kbps to mbps bandwidth converter",
    "calculatorId": "bandwidth-calculator",
    "slug": "kbps-to-mbps-bandwidth-converter"
  },
  {
    "keyword": "leased line bandwidth calculator",
    "calculatorId": "bandwidth-calculator",
    "slug": "leased-line-bandwidth-calculator"
  },
  {
    "keyword": "link bandwidth calculator",
    "calculatorId": "bandwidth-calculator",
    "slug": "link-bandwidth-calculator"
  },
  {
    "keyword": "live streaming data usage calculator",
    "calculatorId": "bandwidth-calculator",
    "slug": "live-streaming-data-usage-calculator"
  },
  {
    "keyword": "lora bitrate calculator",
    "calculatorId": "bandwidth-calculator",
    "slug": "lora-bitrate-calculator"
  },
  {
    "keyword": "mb speed calculator",
    "calculatorId": "bandwidth-calculator",
    "slug": "mb-speed-calculator"
  },
  {
    "keyword": "megabits per second calculator",
    "calculatorId": "bandwidth-calculator",
    "slug": "megabits-per-second-calculator"
  },
  {
    "keyword": "monthly bandwidth calculator",
    "calculatorId": "bandwidth-calculator",
    "slug": "monthly-bandwidth-calculator"
  },
  {
    "keyword": "monthly bandwidth usage calculator",
    "calculatorId": "bandwidth-calculator",
    "slug": "monthly-bandwidth-usage-calculator"
  },
  {
    "keyword": "mpls bandwidth calculator",
    "calculatorId": "bandwidth-calculator",
    "slug": "mpls-bandwidth-calculator"
  },
  {
    "keyword": "net connection speed calculator",
    "calculatorId": "bandwidth-calculator",
    "slug": "net-connection-speed-calculator"
  },
  {
    "keyword": "network bandwidth calculation formula",
    "calculatorId": "bandwidth-calculator",
    "slug": "network-bandwidth-calculation-formula"
  },
  {
    "keyword": "network bandwidth formula",
    "calculatorId": "bandwidth-calculator",
    "slug": "network-bandwidth-formula"
  },
  {
    "keyword": "network calculator bandwidth",
    "calculatorId": "bandwidth-calculator",
    "slug": "network-calculator-bandwidth"
  },
  {
    "keyword": "network speed conversion calculator",
    "calculatorId": "bandwidth-calculator",
    "slug": "network-speed-conversion-calculator"
  },
  {
    "keyword": "network throughput calculation example",
    "calculatorId": "bandwidth-calculator",
    "slug": "network-throughput-calculation-example"
  },
  {
    "keyword": "network traffic calculator",
    "calculatorId": "bandwidth-calculator",
    "slug": "network-traffic-calculator"
  },
  {
    "keyword": "network usage calculator",
    "calculatorId": "bandwidth-calculator",
    "slug": "network-usage-calculator"
  },
  {
    "keyword": "nvr bandwidth calculator",
    "calculatorId": "bandwidth-calculator",
    "slug": "nvr-bandwidth-calculator"
  },
  {
    "keyword": "office bandwidth calculator",
    "calculatorId": "bandwidth-calculator",
    "slug": "office-bandwidth-calculator"
  },
  {
    "keyword": "online network speed calculator",
    "calculatorId": "bandwidth-calculator",
    "slug": "online-network-speed-calculator"
  },
  {
    "keyword": "pcie bandwidth calculator",
    "calculatorId": "bandwidth-calculator",
    "slug": "pcie-bandwidth-calculator"
  },
  {
    "keyword": "pcie speed calculator",
    "calculatorId": "bandwidth-calculator",
    "slug": "pcie-speed-calculator"
  },
  {
    "keyword": "replication bandwidth calculator",
    "calculatorId": "bandwidth-calculator",
    "slug": "replication-bandwidth-calculator"
  },
  {
    "keyword": "security camera bitrate calculator",
    "calculatorId": "bandwidth-calculator",
    "slug": "security-camera-bitrate-calculator"
  },
  {
    "keyword": "server bandwidth calculator",
    "calculatorId": "bandwidth-calculator",
    "slug": "server-bandwidth-calculator"
  },
  {
    "keyword": "signal bandwidth calculator",
    "calculatorId": "bandwidth-calculator",
    "slug": "signal-bandwidth-calculator"
  },
  {
    "keyword": "storage throughput calculator",
    "calculatorId": "bandwidth-calculator",
    "slug": "storage-throughput-calculator"
  },
  {
    "keyword": "stream bandwidth calculator",
    "calculatorId": "bandwidth-calculator",
    "slug": "stream-bandwidth-calculator"
  },
  {
    "keyword": "throughput calculator",
    "calculatorId": "bandwidth-calculator",
    "slug": "throughput-calculator"
  },
  {
    "keyword": "throughput calculator network",
    "calculatorId": "bandwidth-calculator",
    "slug": "throughput-calculator-network"
  },
  {
    "keyword": "throughput calculator online",
    "calculatorId": "bandwidth-calculator",
    "slug": "throughput-calculator-online"
  },
  {
    "keyword": "throughput file transfer calculation",
    "calculatorId": "bandwidth-calculator",
    "slug": "throughput-file-transfer-calculation"
  },
  {
    "keyword": "total bandwidth calculator",
    "calculatorId": "bandwidth-calculator",
    "slug": "total-bandwidth-calculator"
  },
  {
    "keyword": "tron bandwidth calculator",
    "calculatorId": "bandwidth-calculator",
    "slug": "tron-bandwidth-calculator"
  },
  {
    "keyword": "upload and download speed calculator",
    "calculatorId": "bandwidth-calculator",
    "slug": "upload-and-download-speed-calculator"
  },
  {
    "keyword": "upload calculator bandwidth",
    "calculatorId": "bandwidth-calculator",
    "slug": "upload-calculator-bandwidth"
  },
  {
    "keyword": "user bandwidth calculator",
    "calculatorId": "bandwidth-calculator",
    "slug": "user-bandwidth-calculator"
  },
  {
    "keyword": "video codec bandwidth calculator",
    "calculatorId": "bandwidth-calculator",
    "slug": "video-codec-bandwidth-calculator"
  },
  {
    "keyword": "video stream data calculator",
    "calculatorId": "bandwidth-calculator",
    "slug": "video-stream-data-calculator"
  },
  {
    "keyword": "video streaming data usage calculator",
    "calculatorId": "bandwidth-calculator",
    "slug": "video-streaming-data-usage-calculator"
  },
  {
    "keyword": "wan bandwidth calculator",
    "calculatorId": "bandwidth-calculator",
    "slug": "wan-bandwidth-calculator"
  },
  {
    "keyword": "wifi bandwidth calculator",
    "calculatorId": "bandwidth-calculator",
    "slug": "wifi-bandwidth-calculator"
  },
  {
    "keyword": "wifi speed calculator online",
    "calculatorId": "bandwidth-calculator",
    "slug": "wifi-speed-calculator-online"
  },
  {
    "keyword": "wifi speed test mb s",
    "calculatorId": "bandwidth-calculator",
    "slug": "wifi-speed-test-mb-s"
  },
  {
    "keyword": "wireless bandwidth calculator",
    "calculatorId": "bandwidth-calculator",
    "slug": "wireless-bandwidth-calculator"
  },
  {
    "keyword": "wistia bandwidth calculator",
    "calculatorId": "bandwidth-calculator",
    "slug": "wistia-bandwidth-calculator"
  },
  {
    "keyword": "zerto bandwidth calculator",
    "calculatorId": "bandwidth-calculator",
    "slug": "zerto-bandwidth-calculator"
  }
]